federated_learn/__init__.py
federated_learn/dataseMaker.py
federated_learn/main.py
federated_learn/model.py
federated_learn/trainer.py
federated_learn-1.0.1.dist-info/METADATA
federated_learn-1.0.1.dist-info/WHEEL
federated_learn-1.0.1.dist-info/top_level.txt
federated_learn-1.0.1.dist-info/RECORD
